dedupeflow/__init__.py
dedupeflow/cli.py
dedupeflow/data.json
dedupeflow/numeric.py
dedupeflow-0.0.1.dist-info/METADATA
dedupeflow-0.0.1.dist-info/WHEEL
dedupeflow-0.0.1.dist-info/entry_points.txt
dedupeflow-0.0.1.dist-info/top_level.txt
dedupeflow-0.0.1.dist-info/RECORD
